<annotation>
	<folder>airplane_1000</folder>
	<filename>airplane1976.jpg</filename>
	<path>C:\Users\Çağla	Sevindik\Desktop\airplane_1000\airplane1976.jpg</path>
	<source>
		<database>Unknown</database>
	</source>
	<size>
		<width>375</width>
		<height>375</height>
		<depth>1</depth>
	</size>
	<segmented>0</segmented>
	<object>
		<name>airplane</name>
		<pose>Unspecified</pose>
		<truncated>0</truncated>
		<difficult>0</difficult>
		<bndbox>
			<xmin>7</xmin>
			<ymin>16</ymin>
			<xmax>363</xmax>
			<ymax>359</ymax>
		</bndbox>
	</object>
</annotation>
