<annotation>
	<folder>car_1500</folder>
	<filename>car-1292.jpg</filename>
	<path>C:\Users\Çağla	Sevindik\Desktop\car_1500\car-1292.jpg</path>
	<source>
		<database>Unknown</database>
	</source>
	<size>
		<width>375</width>
		<height>375</height>
		<depth>1</depth>
	</size>
	<segmented>0</segmented>
	<object>
		<name>car</name>
		<pose>Unspecified</pose>
		<truncated>0</truncated>
		<difficult>0</difficult>
		<bndbox>
			<xmin>220</xmin>
			<ymin>56</ymin>
			<xmax>320</xmax>
			<ymax>103</ymax>
		</bndbox>
	</object>
	<object>
		<name>car</name>
		<pose>Unspecified</pose>
		<truncated>0</truncated>
		<difficult>0</difficult>
		<bndbox>
			<xmin>64</xmin>
			<ymin>76</ymin>
			<xmax>173</xmax>
			<ymax>128</ymax>
		</bndbox>
	</object>
	<object>
		<name>car</name>
		<pose>Unspecified</pose>
		<truncated>0</truncated>
		<difficult>0</difficult>
		<bndbox>
			<xmin>206</xmin>
			<ymin>245</ymin>
			<xmax>319</xmax>
			<ymax>321</ymax>
		</bndbox>
	</object>
	<object>
		<name>car</name>
		<pose>Unspecified</pose>
		<truncated>0</truncated>
		<difficult>0</difficult>
		<bndbox>
			<xmin>38</xmin>
			<ymin>240</ymin>
			<xmax>154</xmax>
			<ymax>308</ymax>
		</bndbox>
	</object>
	<object>
		<name>car</name>
		<pose>Unspecified</pose>
		<truncated>1</truncated>
		<difficult>0</difficult>
		<bndbox>
			<xmin>283</xmin>
			<ymin>255</ymin>
			<xmax>375</xmax>
			<ymax>355</ymax>
		</bndbox>
	</object>
	<object>
		<name>car</name>
		<pose>Unspecified</pose>
		<truncated>0</truncated>
		<difficult>0</difficult>
		<bndbox>
			<xmin>158</xmin>
			<ymin>255</ymin>
			<xmax>227</xmax>
			<ymax>288</ymax>
		</bndbox>
	</object>
</annotation>
