<annotation>
	<folder>car2500</folder>
	<filename>car3468.jpg</filename>
	<path>C:\Users\Çağla	Sevindik\Desktop\car2500\car3468.jpg</path>
	<source>
		<database>Unknown</database>
	</source>
	<size>
		<width>375</width>
		<height>375</height>
		<depth>1</depth>
	</size>
	<segmented>0</segmented>
	<object>
		<name>car</name>
		<pose>Unspecified</pose>
		<truncated>0</truncated>
		<difficult>0</difficult>
		<bndbox>
			<xmin>10</xmin>
			<ymin>139</ymin>
			<xmax>357</xmax>
			<ymax>331</ymax>
		</bndbox>
	</object>
</annotation>
