<annotation>
	<folder>Train_Dog</folder>
	<filename>dog-643.jpg</filename>
	<path>C:\Users\Çağla	Sevindik\Desktop\olanlar\Train_Dog\dog-643.jpg</path>
	<source>
		<database>Unknown</database>
	</source>
	<size>
		<width>375</width>
		<height>375</height>
		<depth>1</depth>
	</size>
	<segmented>0</segmented>
	<object>
		<name>dog</name>
		<pose>Unspecified</pose>
		<truncated>0</truncated>
		<difficult>0</difficult>
		<bndbox>
			<xmin>32</xmin>
			<ymin>11</ymin>
			<xmax>236</xmax>
			<ymax>352</ymax>
		</bndbox>
	</object>
</annotation>
