<annotation>
	<folder>Train_Cat</folder>
	<filename>small_1245.jpeg</filename>
	<path>C:\Users\Çağla	Sevindik\Desktop\Train_Cat\small_1245.jpeg</path>
	<source>
		<database>Unknown</database>
	</source>
	<size>
		<width>375</width>
		<height>375</height>
		<depth>1</depth>
	</size>
	<segmented>0</segmented>
	<object>
		<name>cat</name>
		<pose>Unspecified</pose>
		<truncated>0</truncated>
		<difficult>0</difficult>
		<bndbox>
			<xmin>205</xmin>
			<ymin>5</ymin>
			<xmax>323</xmax>
			<ymax>354</ymax>
		</bndbox>
	</object>
	<object>
		<name>cat</name>
		<pose>Unspecified</pose>
		<truncated>0</truncated>
		<difficult>0</difficult>
		<bndbox>
			<xmin>27</xmin>
			<ymin>172</ymin>
			<xmax>265</xmax>
			<ymax>364</ymax>
		</bndbox>
	</object>
</annotation>
